{"graph_1": [[0, 1], [0, 2], [0, 3], [2, 4], [2, 5], [1, 6], [1, 7], [1, 8], [2, 9], [1, 10], [1, 11], [1, 12], [2, 13], [2, 14], [2, 15], [2, 16], [2, 17], [2, 18], [2, 19], [2, 20], [1, 21], [1, 22], [3, 23], [2, 24], [3, 25], [1, 26], [1, 27]], "graph_2": [[0, 1], [0, 2], [0, 3], [1, 4], [1, 5], [1, 6], [2, 7], [2, 8], [1, 9], [2, 10], [2, 11], [1, 12], [1, 13], [1, 14], [1, 15], [1, 16], [1, 17], [1, 18], [1, 19], [1, 20], [3, 21], [2, 22], [3, 23], [2, 24], [1, 25], [2, 26], [1, 27], [1, 28], [1, 29], [1, 30], [1, 31], [1, 32], [2, 33], [1, 34], [1, 35], [1, 36]], "labels_1": ["U:10392", "High", "Medium", "Low", "M:1", "M:5", "M:7", "M:17", "M:18", "M:32", "M:107", "M:141", "M:260", "M:628", "M:648", "M:653", "M:708", "M:724", "M:733", "M:736", "M:761", "M:780", "M:783", "M:786", "M:830", "M:849", "M:1073", "M:1210"], "labels_2": ["U:10393", "High", "Medium", "Low", "M:70", "M:111", "M:260", "M:356", "M:367", "M:720", "M:920", "M:1036", "M:1073", "M:1136", "M:1193", "M:1199", "M:1210", "M:1256", "M:1266", "M:1280", "M:1281", "M:1967", "M:2100", "M:2140", "M:2174", "M:2628", "M:2648", "M:2968", "M:3086", "M:3133", "M:3204", "M:3307", "M:3310", "M:3404", "M:3462", "M:3624", "M:3629"], "ged": 53}