{"graph_1": [[0, 1], [0, 2], [0, 3], [1, 4], [1, 5], [1, 6], [1, 7], [1, 8], [3, 9], [3, 10], [2, 11], [1, 12], [1, 13], [3, 14], [2, 15], [1, 16], [2, 17], [1, 18], [3, 19], [3, 20], [1, 21], [1, 22], [3, 23], [3, 24], [2, 25], [2, 26], [3, 27], [3, 28], [1, 29], [2, 30], [2, 31], [1, 32], [2, 33], [1, 34], [1, 35], [1, 36], [1, 37], [1, 38], [1, 39], [1, 40], [1, 41], [3, 42], [1, 43], [1, 44], [1, 45], [1, 46], [1, 47], [1, 48], [1, 49], [2, 50], [1, 51], [1, 52], [1, 53], [1, 54], [1, 55], [3, 56], [2, 57], [1, 58], [1, 59], [1, 60], [1, 61], [3, 62], [3, 63], [3, 64], [2, 65], [1, 66], [2, 67], [2, 68], [2, 69], [1, 70], [1, 71], [1, 72], [3, 73], [2, 74], [2, 75], [1, 76], [3, 77], [1, 78], [2, 79], [1, 80], [3, 81], [2, 82], [1, 83], [1, 84], [3, 85], [1, 86], [1, 87], [1, 88], [3, 89], [1, 90], [3, 91], [1, 92], [1, 93], [1, 94]], "graph_2": [[0, 1], [0, 2], [0, 3], [1, 4], [1, 5], [2, 6], [1, 7], [1, 8], [3, 9], [3, 10], [1, 11], [2, 12], [1, 13], [1, 14], [1, 15], [1, 16], [1, 17], [1, 18], [1, 19], [2, 20], [2, 21], [1, 22], [3, 23], [2, 24], [1, 25], [1, 26], [1, 27], [2, 28], [2, 29], [3, 30], [1, 31], [1, 32], [1, 33], [2, 34], [1, 35], [2, 36], [1, 37], [2, 38], [1, 39], [3, 40], [1, 41], [3, 42], [3, 43], [1, 44], [1, 45], [3, 46], [3, 47], [1, 48], [1, 49], [1, 50], [1, 51], [1, 52], [1, 53], [1, 54], [3, 55], [3, 56], [2, 57], [1, 58], [3, 59], [1, 60], [1, 61], [3, 62], [2, 63], [1, 64], [2, 65], [2, 66]], "labels_1": ["U:10432", "High", "Medium", "Low", "M:1", "M:2", "M:3", "M:5", "M:7", "M:9", "M:12", "M:14", "M:18", "M:21", "M:25", "M:32", "M:52", "M:58", "M:62", "M:65", "M:66", "M:76", "M:86", "M:88", "M:94", "M:95", "M:100", "M:102", "M:104", "M:107", "M:110", "M:112", "M:135", "M:140", "M:141", "M:150", "M:151", "M:236", "M:260", "M:316", "M:349", "M:356", "M:376", "M:380", "M:440", "M:454", "M:457", "M:480", "M:494", "M:500", "M:586", "M:587", "M:589", "M:590", "M:608", "M:628", "M:631", "M:637", "M:640", "M:647", "M:648", "M:653", "M:661", "M:667", "M:671", "M:673", "M:707", "M:708", "M:711", "M:719", "M:724", "M:733", "M:736", "M:737", "M:743", "M:747", "M:748", "M:761", "M:762", "M:778", "M:780", "M:783", "M:784", "M:785", "M:786", "M:788", "M:802", "M:805", "M:832", "M:839", "M:852", "M:1073", "M:1210", "M:1356", "M:1393"], "labels_2": ["U:10433", "High", "Medium", "Low", "M:1", "M:110", "M:150", "M:225", "M:231", "M:260", "M:296", "M:318", "M:356", "M:380", "M:434", "M:457", "M:524", "M:527", "M:539", "M:597", "M:986", "M:1031", "M:1073", "M:1210", "M:1381", "M:1580", "M:1625", "M:1721", "M:1958", "M:2501", "M:2571", "M:2605", "M:2686", "M:2881", "M:3100", "M:3114", "M:3450", "M:3578", "M:3624", "M:4226", "M:4703", "M:4886", "M:4992", "M:4993", "M:5293", "M:5418", "M:5952", "M:7153", "M:8132", "M:8533", "M:8665", "M:26791", "M:31685", "M:52604", "M:54286", "M:56949", "M:58559", "M:59315", "M:60069", "M:60756", "M:63082", "M:64716", "M:68358", "M:68954", "M:70286", "M:78499", "M:79132"], "ged": 138}