{"graph_1": [[0, 1], [0, 2], [0, 3], [2, 4], [1, 5], [1, 6], [1, 7], [1, 8], [1, 9], [1, 10], [1, 11], [1, 12], [1, 13], [1, 14], [1, 15], [1, 16], [1, 17], [2, 18], [3, 19], [2, 20], [3, 21], [2, 22], [2, 23], [1, 24], [1, 25], [1, 26], [3, 27], [3, 28]], "graph_2": [[0, 1], [0, 2], [0, 3], [1, 4], [2, 5], [1, 6], [1, 7], [1, 8], [1, 9], [1, 10], [1, 11], [1, 12], [1, 13], [1, 14], [1, 15], [2, 16], [1, 17], [2, 18], [1, 19], [2, 20], [2, 21], [1, 22], [1, 23]], "labels_1": ["U:12093", "High", "Medium", "Low", "M:145", "M:2706", "M:52973", "M:59784", "M:87869", "M:93510", "M:122904", "M:122912", "M:138036", "M:168252", "M:187593", "M:187613", "M:187723", "M:191351", "M:191869", "M:192393", "M:192579", "M:192697", "M:194194", "M:194696", "M:195639", "M:195723", "M:195725", "M:197127", "M:197725"], "labels_2": ["U:12094", "High", "Medium", "Low", "M:260", "M:431", "M:1193", "M:1197", "M:1203", "M:1249", "M:1261", "M:1287", "M:1927", "M:2405", "M:2455", "M:2944", "M:3053", "M:3702", "M:3826", "M:3917", "M:3998", "M:4247", "M:4467", "M:7153"], "ged": 47}