{"graph_1": [[0, 1], [0, 2], [0, 3], [1, 4], [1, 5], [1, 6], [1, 7], [1, 8], [1, 9], [1, 10], [2, 11], [1, 12], [1, 13], [2, 14], [1, 15], [2, 16], [1, 17], [1, 18], [3, 19], [2, 20], [2, 21], [1, 22], [1, 23], [2, 24], [2, 25], [1, 26], [1, 27], [2, 28], [1, 29], [1, 30], [1, 31], [1, 32], [1, 33], [2, 34], [1, 35], [1, 36]], "graph_2": [[0, 1], [0, 2], [0, 3], [1, 4], [1, 5], [2, 6], [1, 7], [1, 8], [2, 9], [1, 10], [1, 11], [1, 12], [1, 13], [3, 14], [1, 15], [2, 16], [1, 17], [3, 18], [3, 19], [2, 20], [2, 21], [2, 22], [1, 23], [1, 24], [1, 25], [1, 26], [1, 27], [1, 28], [2, 29], [1, 30], [1, 31]], "labels_1": ["U:12838", "High", "Medium", "Low", "M:1", "M:17", "M:32", "M:36", "M:58", "M:62", "M:82", "M:112", "M:116", "M:260", "M:581", "M:608", "M:640", "M:647", "M:745", "M:778", "M:781", "M:832", "M:838", "M:858", "M:866", "M:994", "M:1041", "M:1042", "M:1073", "M:1210", "M:1233", "M:1356", "M:1407", "M:1416", "M:1429", "M:1527", "M:1580"], "labels_2": ["U:12839", "High", "Medium", "Low", "M:1", "M:296", "M:356", "M:527", "M:2324", "M:2571", "M:2959", "M:4886", "M:4973", "M:6016", "M:6333", "M:6377", "M:6539", "M:7147", "M:8360", "M:8636", "M:8874", "M:8961", "M:44191", "M:60069", "M:68157", "M:78499", "M:79132", "M:79702", "M:92259", "M:116797", "M:158966", "M:168252"], "ged": 61}