{"graph_1": [[0, 1], [0, 2], [0, 3], [3, 4], [2, 5], [2, 6], [3, 7], [3, 8], [3, 9], [3, 10], [1, 11], [3, 12], [3, 13], [1, 14], [3, 15], [3, 16], [3, 17], [2, 18], [1, 19], [3, 20], [3, 21], [3, 22], [1, 23]], "graph_2": [[0, 1], [0, 2], [0, 3], [1, 4], [2, 5], [3, 6], [2, 7], [2, 8], [2, 9], [2, 10], [2, 11], [1, 12], [1, 13], [2, 14], [1, 15], [1, 16], [1, 17], [1, 18], [1, 19], [1, 20], [1, 21], [1, 22], [1, 23], [1, 24], [1, 25], [1, 26], [1, 27], [2, 28], [2, 29], [3, 30], [1, 31]], "labels_1": ["U:12927", "High", "Medium", "Low", "M:194", "M:303", "M:532", "M:637", "M:671", "M:1077", "M:1296", "M:1957", "M:2087", "M:2109", "M:2160", "M:2243", "M:2352", "M:2359", "M:2501", "M:2707", "M:2944", "M:2948", "M:3363", "M:27815"], "labels_2": ["U:12928", "High", "Medium", "Low", "M:32", "M:193", "M:327", "M:531", "M:562", "M:799", "M:830", "M:1409", "M:2141", "M:2142", "M:2145", "M:2231", "M:2329", "M:2572", "M:2686", "M:2706", "M:2717", "M:2795", "M:2881", "M:3105", "M:3148", "M:3535", "M:3863", "M:4718", "M:7541", "M:33085", "M:45361", "M:53953"], "ged": 50}