{"graph_1": [[0, 1], [0, 2], [0, 3], [2, 4], [2, 5], [3, 6], [1, 7], [3, 8], [2, 9], [2, 10], [2, 11], [1, 12], [1, 13], [1, 14], [3, 15], [1, 16], [2, 17], [2, 18], [1, 19], [1, 20], [3, 21], [1, 22], [1, 23], [2, 24], [2, 25], [2, 26], [1, 27], [2, 28], [2, 29], [2, 30]], "graph_2": [[0, 1], [0, 2], [0, 3], [3, 4], [3, 5], [3, 6], [3, 7], [3, 8], [3, 9], [2, 10], [3, 11], [2, 12], [2, 13], [3, 14], [2, 15], [3, 16], [2, 17], [3, 18], [3, 19], [3, 20], [3, 21], [3, 22], [3, 23]], "labels_1": ["U:13369", "High", "Medium", "Low", "M:1729", "M:1882", "M:2167", "M:2571", "M:58559", "M:63113", "M:68319", "M:97913", "M:102903", "M:111759", "M:112852", "M:119145", "M:122910", "M:122912", "M:122914", "M:122916", "M:122918", "M:134130", "M:140110", "M:162606", "M:168252", "M:179401", "M:194016", "M:197175", "M:200306", "M:200540", "M:200818"], "labels_2": ["U:13370", "High", "Medium", "Low", "M:170", "M:348", "M:362", "M:524", "M:610", "M:968", "M:1032", "M:1093", "M:1186", "M:1188", "M:1223", "M:1231", "M:1244", "M:1261", "M:1831", "M:1912", "M:2288", "M:3510", "M:3624", "M:6863"], "ged": 49}