{"graph_1": [[0, 1], [0, 2], [0, 3], [2, 4], [2, 5], [3, 6], [2, 7], [1, 8], [3, 9], [3, 10], [3, 11], [1, 12], [1, 13], [1, 14], [1, 15], [1, 16], [1, 17], [1, 18], [3, 19], [1, 20], [1, 21], [3, 22], [1, 23], [1, 24], [2, 25], [3, 26], [3, 27], [3, 28], [3, 29], [3, 30]], "graph_2": [[0, 1], [0, 2], [0, 3], [3, 4], [2, 5], [2, 6], [1, 7], [1, 8], [2, 9], [3, 10], [1, 11], [1, 12], [3, 13], [1, 14], [2, 15], [1, 16], [1, 17], [2, 18], [2, 19], [2, 20], [3, 21], [2, 22], [1, 23]], "labels_1": ["U:13654", "High", "Medium", "Low", "M:260", "M:318", "M:527", "M:1196", "M:1197", "M:1198", "M:2571", "M:2959", "M:4896", "M:4993", "M:5952", "M:7153", "M:8368", "M:40815", "M:54001", "M:58559", "M:69844", "M:81834", "M:84152", "M:88125", "M:98809", "M:122920", "M:122926", "M:167564", "M:171757", "M:172547", "M:175187"], "labels_2": ["U:13655", "High", "Medium", "Low", "M:145", "M:292", "M:543", "M:1127", "M:1276", "M:1285", "M:1320", "M:1396", "M:1408", "M:1673", "M:1674", "M:1909", "M:2100", "M:2194", "M:2302", "M:2692", "M:2770", "M:3052", "M:3623", "M:5952"], "ged": 47}