{"graph_1": [[0, 1], [0, 2], [0, 3], [1, 4], [1, 5], [2, 6], [1, 7], [1, 8], [1, 9], [2, 10], [2, 11], [1, 12], [1, 13], [1, 14], [1, 15], [1, 16], [1, 17], [1, 18], [3, 19], [1, 20], [1, 21], [1, 22], [1, 23], [3, 24], [1, 25], [2, 26], [1, 27], [1, 28], [1, 29], [1, 30]], "graph_2": [[0, 1], [0, 2], [0, 3], [1, 4], [1, 5], [1, 6], [2, 7], [2, 8], [1, 9], [1, 10], [1, 11], [2, 12], [3, 13], [3, 14], [2, 15], [2, 16], [3, 17], [1, 18], [2, 19], [1, 20], [2, 21], [2, 22], [2, 23], [1, 24], [1, 25], [2, 26], [2, 27]], "labels_1": ["U:21707", "High", "Medium", "Low", "M:405", "M:575", "M:637", "M:778", "M:1198", "M:1252", "M:1772", "M:2078", "M:2139", "M:2142", "M:2571", "M:2728", "M:2857", "M:2858", "M:2959", "M:3593", "M:3639", "M:3735", "M:3861", "M:4226", "M:4321", "M:4993", "M:5693", "M:5952", "M:6016", "M:7153", "M:58559"], "labels_2": ["U:21708", "High", "Medium", "Low", "M:1", "M:3", "M:6", "M:7", "M:32", "M:95", "M:112", "M:260", "M:494", "M:608", "M:637", "M:648", "M:653", "M:707", "M:708", "M:733", "M:736", "M:743", "M:780", "M:786", "M:802", "M:805", "M:1073", "M:1356"], "ged": 51}