{"graph_1": [[0, 1], [0, 2], [0, 3], [2, 4], [2, 5], [1, 6], [2, 7], [1, 8], [3, 9], [1, 10], [1, 11], [2, 12], [1, 13], [1, 14], [2, 15], [1, 16], [1, 17], [1, 18], [3, 19], [3, 20], [3, 21], [3, 22], [2, 23], [2, 24], [3, 25], [1, 26], [2, 27], [1, 28], [1, 29], [1, 30], [3, 31], [2, 32], [1, 33], [1, 34], [1, 35], [2, 36], [2, 37], [2, 38], [1, 39], [1, 40], [1, 41], [2, 42], [3, 43], [3, 44], [3, 45], [2, 46], [2, 47], [2, 48], [2, 49], [2, 50], [2, 51], [2, 52], [2, 53], [3, 54], [2, 55], [2, 56], [2, 57], [1, 58], [1, 59], [2, 60], [2, 61], [2, 62], [1, 63], [1, 64], [1, 65], [2, 66], [1, 67], [1, 68], [2, 69], [1, 70], [1, 71], [1, 72], [1, 73], [2, 74], [2, 75], [2, 76], [1, 77], [2, 78], [3, 79], [2, 80], [2, 81], [3, 82], [1, 83], [1, 84], [2, 85], [2, 86], [1, 87], [2, 88], [1, 89], [2, 90], [2, 91], [1, 92], [2, 93], [2, 94], [1, 95], [2, 96], [1, 97], [2, 98], [1, 99], [3, 100], [2, 101], [2, 102], [2, 103], [2, 104], [2, 105], [2, 106], [2, 107], [2, 108], [2, 109], [2, 110], [1, 111], [2, 112], [2, 113], [1, 114], [1, 115], [1, 116], [2, 117], [1, 118], [1, 119], [2, 120], [1, 121], [1, 122], [2, 123], [2, 124], [2, 125], [2, 126], [1, 127], [1, 128], [2, 129], [1, 130], [3, 131], [3, 132], [2, 133], [1, 134], [2, 135], [1, 136], [2, 137], [2, 138], [2, 139], [3, 140], [2, 141], [2, 142], [2, 143], [2, 144], [2, 145], [1, 146], [1, 147], [1, 148], [2, 149], [2, 150], [1, 151], [2, 152]], "graph_2": [[0, 1], [0, 2], [0, 3], [2, 4], [1, 5], [1, 6], [1, 7], [1, 8], [1, 9], [1, 10], [1, 11], [1, 12], [2, 13], [1, 14], [1, 15], [1, 16], [2, 17], [1, 18], [1, 19], [1, 20], [1, 21], [2, 22], [2, 23], [1, 24], [1, 25], [1, 26], [1, 27], [1, 28], [2, 29], [2, 30], [1, 31], [2, 32], [1, 33], [1, 34], [1, 35], [1, 36], [1, 37], [1, 38], [1, 39], [2, 40], [1, 41]], "labels_1": ["U:22048", "High", "Medium", "Low", "M:6", "M:10", "M:11", "M:16", "M:17", "M:20", "M:21", "M:22", "M:23", "M:32", "M:36", "M:39", "M:45", "M:47", "M:50", "M:61", "M:70", "M:73", "M:76", "M:79", "M:89", "M:93", "M:95", "M:100", "M:110", "M:111", "M:112", "M:132", "M:135", "M:141", "M:150", "M:151", "M:153", "M:155", "M:160", "M:161", "M:163", "M:164", "M:165", "M:168", "M:172", "M:173", "M:185", "M:196", "M:198", "M:204", "M:208", "M:223", "M:225", "M:227", "M:228", "M:229", "M:230", "M:234", "M:235", "M:236", "M:252", "M:256", "M:257", "M:259", "M:260", "M:272", "M:273", "M:280", "M:281", "M:288", "M:292", "M:293", "M:296", "M:300", "M:303", "M:315", "M:316", "M:318", "M:327", "M:328", "M:329", "M:338", "M:344", "M:345", "M:348", "M:349", "M:350", "M:353", "M:356", "M:357", "M:360", "M:367", "M:368", "M:370", "M:371", "M:373", "M:376", "M:377", "M:380", "M:382", "M:383", "M:410", "M:415", "M:416", "M:419", "M:420", "M:427", "M:428", "M:431", "M:434", "M:435", "M:440", "M:442", "M:448", "M:452", "M:454", "M:457", "M:466", "M:468", "M:471", "M:474", "M:475", "M:480", "M:485", "M:489", "M:490", "M:491", "M:494", "M:508", "M:509", "M:514", "M:519", "M:520", "M:524", "M:527", "M:528", "M:529", "M:532", "M:533", "M:535", "M:540", "M:543", "M:544", "M:548", "M:552", "M:553", "M:555", "M:587", "M:589", "M:590", "M:592", "M:593", "M:648"], "labels_2": ["U:22049", "High", "Medium", "Low", "M:223", "M:296", "M:356", "M:1207", "M:1246", "M:1258", "M:1285", "M:1968", "M:2114", "M:2291", "M:2858", "M:3556", "M:4878", "M:33171", "M:46578", "M:53318", "M:56367", "M:59549", "M:69757", "M:72720", "M:79357", "M:80693", "M:91199", "M:96821", "M:97921", "M:103606", "M:104944", "M:105355", "M:105869", "M:109181", "M:111387", "M:115770", "M:117176", "M:120392", "M:129781", "M:129943", "M:141950", "M:145299"], "ged": 183}