{"graph_1": [[0, 1], [0, 2], [0, 3], [1, 4], [2, 5], [2, 6], [3, 7], [2, 8], [2, 9], [1, 10], [3, 11], [2, 12], [2, 13], [1, 14], [3, 15], [2, 16], [1, 17], [1, 18], [1, 19], [2, 20], [1, 21], [1, 22], [1, 23], [2, 24], [1, 25]], "graph_2": [[0, 1], [0, 2], [0, 3], [2, 4], [1, 5], [2, 6], [2, 7], [1, 8], [1, 9], [1, 10], [1, 11], [2, 12], [1, 13], [3, 14], [3, 15], [3, 16], [3, 17], [2, 18], [3, 19], [2, 20], [2, 21], [1, 22], [1, 23], [1, 24], [2, 25], [1, 26], [1, 27], [2, 28], [1, 29], [1, 30], [1, 31], [2, 32], [1, 33], [2, 34], [1, 35], [1, 36], [2, 37], [1, 38], [1, 39], [1, 40], [2, 41], [1, 42], [1, 43], [1, 44], [2, 45], [1, 46], [1, 47], [1, 48], [1, 49], [1, 50], [3, 51], [2, 52], [1, 53], [2, 54], [2, 55]], "labels_1": ["U:23408", "High", "Medium", "Low", "M:1", "M:32", "M:86", "M:95", "M:100", "M:141", "M:608", "M:648", "M:661", "M:736", "M:780", "M:784", "M:786", "M:805", "M:860", "M:1046", "M:1059", "M:1073", "M:1120", "M:1357", "M:1367", "M:1393"], "labels_2": ["U:23409", "High", "Medium", "Low", "M:1", "M:47", "M:260", "M:296", "M:318", "M:356", "M:480", "M:527", "M:589", "M:593", "M:858", "M:1197", "M:1198", "M:1221", "M:1270", "M:1291", "M:1704", "M:2028", "M:2329", "M:2571", "M:2762", "M:2858", "M:2959", "M:3147", "M:3578", "M:3793", "M:4306", "M:4886", "M:4993", "M:4995", "M:5418", "M:5952", "M:6539", "M:7153", "M:8961", "M:33794", "M:50872", "M:54286", "M:58559", "M:59315", "M:60069", "M:63082", "M:68954", "M:70286", "M:72998", "M:81845", "M:91529", "M:106782", "M:109487", "M:111759", "M:134130", "M:134853"], "ged": 74}