{"graph_1": [[0, 1], [0, 2], [0, 3], [1, 4], [1, 5], [1, 6], [1, 7], [1, 8], [1, 9], [1, 10], [1, 11], [2, 12], [1, 13], [1, 14], [1, 15], [1, 16], [1, 17], [1, 18], [1, 19], [3, 20], [2, 21], [1, 22], [1, 23], [3, 24], [1, 25], [1, 26], [1, 27], [1, 28], [1, 29], [1, 30], [1, 31], [1, 32], [2, 33], [1, 34], [2, 35], [2, 36], [2, 37], [2, 38], [2, 39], [1, 40], [1, 41], [2, 42], [2, 43], [1, 44], [2, 45], [2, 46], [2, 47]], "graph_2": [[0, 1], [0, 2], [0, 3], [2, 4], [1, 5], [1, 6], [1, 7], [2, 8], [1, 9], [1, 10], [1, 11], [1, 12], [1, 13], [1, 14], [1, 15], [1, 16], [1, 17], [1, 18], [1, 19], [1, 20], [1, 21], [1, 22], [1, 23], [1, 24], [1, 25], [1, 26], [2, 27], [1, 28], [1, 29], [1, 30], [2, 31], [2, 32], [2, 33], [1, 34], [2, 35], [3, 36], [3, 37]], "labels_1": ["U:25566", "High", "Medium", "Low", "M:47", "M:293", "M:356", "M:750", "M:923", "M:1014", "M:1193", "M:1201", "M:1203", "M:1204", "M:1208", "M:1209", "M:1217", "M:1237", "M:1732", "M:2019", "M:2028", "M:2843", "M:2858", "M:2959", "M:3415", "M:5291", "M:5971", "M:5995", "M:7256", "M:7327", "M:7361", "M:26150", "M:55820", "M:58306", "M:81845", "M:99114", "M:109374", "M:109487", "M:112552", "M:115713", "M:116138", "M:122882", "M:136562", "M:139385", "M:143245", "M:144058", "M:149406", "M:152081"], "labels_2": ["U:25567", "High", "Medium", "Low", "M:110", "M:111", "M:223", "M:260", "M:356", "M:551", "M:562", "M:574", "M:648", "M:663", "M:1060", "M:1197", "M:1210", "M:1265", "M:1288", "M:1394", "M:1449", "M:1517", "M:1923", "M:1997", "M:2282", "M:2289", "M:2318", "M:2596", "M:2804", "M:2997", "M:3114", "M:3578", "M:3618", "M:3745", "M:3751", "M:3755", "M:3824", "M:3863"], "ged": 78}