{"graph_1": [[0, 1], [0, 2], [0, 3], [2, 4], [1, 5], [2, 6], [3, 7], [1, 8], [1, 9], [3, 10], [1, 11], [1, 12], [1, 13], [2, 14], [3, 15], [2, 16], [1, 17], [1, 18], [3, 19], [3, 20], [1, 21], [3, 22], [3, 23], [1, 24], [1, 25], [3, 26], [1, 27], [1, 28], [1, 29], [1, 30], [1, 31], [3, 32], [2, 33], [3, 34], [1, 35], [3, 36]], "graph_2": [[0, 1], [0, 2], [0, 3], [1, 4], [2, 5], [2, 6], [1, 7], [3, 8], [2, 9], [1, 10], [2, 11], [3, 12], [2, 13], [1, 14], [3, 15], [1, 16], [1, 17], [2, 18], [1, 19], [2, 20], [1, 21], [1, 22], [1, 23], [1, 24], [1, 25], [1, 26], [1, 27], [1, 28], [1, 29], [2, 30], [1, 31], [3, 32], [1, 33], [3, 34], [3, 35], [1, 36], [3, 37]], "labels_1": ["U:26172", "High", "Medium", "Low", "M:110", "M:260", "M:1907", "M:2028", "M:4896", "M:5816", "M:6333", "M:7143", "M:8368", "M:41566", "M:50872", "M:56152", "M:58559", "M:59315", "M:59501", "M:60069", "M:68954", "M:69844", "M:74458", "M:78499", "M:81834", "M:82169", "M:86644", "M:88125", "M:106002", "M:115617", "M:122912", "M:122916", "M:134853", "M:135143", "M:177765", "M:180095", "M:185029"], "labels_2": ["U:26173", "High", "Medium", "Low", "M:110", "M:151", "M:161", "M:260", "M:266", "M:356", "M:389", "M:780", "M:991", "M:1090", "M:1094", "M:1183", "M:1200", "M:1204", "M:1208", "M:1210", "M:1222", "M:1224", "M:1242", "M:1250", "M:1262", "M:1263", "M:1272", "M:1298", "M:1299", "M:1408", "M:1619", "M:1920", "M:1960", "M:2028", "M:2402", "M:2404", "M:2427", "M:2542"], "ged": 63}