{"graph_1": [[0, 1], [0, 2], [0, 3], [2, 4], [1, 5], [1, 6], [1, 7], [1, 8], [1, 9], [1, 10], [1, 11], [1, 12], [3, 13], [1, 14], [1, 15], [1, 16], [1, 17], [1, 18], [1, 19], [1, 20], [1, 21], [3, 22], [1, 23], [1, 24], [1, 25], [1, 26], [1, 27], [1, 28], [2, 29], [1, 30], [3, 31], [1, 32], [1, 33], [1, 34], [1, 35], [1, 36], [2, 37], [1, 38], [3, 39], [2, 40], [2, 41], [1, 42], [1, 43], [1, 44], [3, 45], [1, 46], [2, 47], [1, 48], [1, 49], [1, 50], [1, 51], [1, 52], [1, 53], [1, 54], [2, 55], [1, 56], [1, 57], [3, 58], [1, 59], [1, 60]], "graph_2": [[0, 1], [0, 2], [0, 3], [3, 4], [3, 5], [2, 6], [3, 7], [2, 8], [3, 9], [3, 10], [2, 11], [1, 12], [3, 13], [2, 14], [2, 15], [1, 16], [2, 17], [2, 18], [1, 19], [2, 20], [2, 21], [1, 22], [2, 23], [3, 24], [3, 25], [2, 26], [3, 27], [2, 28], [2, 29], [2, 30], [2, 31], [3, 32], [3, 33], [2, 34], [1, 35], [2, 36], [2, 37], [2, 38], [3, 39], [2, 40], [3, 41], [3, 42], [2, 43], [1, 44], [2, 45], [3, 46], [1, 47], [2, 48], [1, 49], [3, 50], [2, 51], [1, 52], [2, 53], [3, 54], [3, 55], [2, 56], [3, 57], [3, 58], [2, 59], [3, 60], [3, 61], [3, 62], [1, 63], [2, 64], [1, 65], [3, 66], [1, 67], [1, 68], [1, 69], [1, 70], [1, 71], [2, 72]], "labels_1": ["U:27471", "High", "Medium", "Low", "M:19", "M:260", "M:344", "M:345", "M:410", "M:589", "M:596", "M:750", "M:913", "M:924", "M:940", "M:950", "M:965", "M:969", "M:1019", "M:1127", "M:1196", "M:1199", "M:1206", "M:1212", "M:1214", "M:1240", "M:1252", "M:1253", "M:1270", "M:1274", "M:1284", "M:1503", "M:1541", "M:1645", "M:2010", "M:2015", "M:2072", "M:2085", "M:2124", "M:2126", "M:2287", "M:2492", "M:2571", "M:2660", "M:2664", "M:2817", "M:3070", "M:3072", "M:3153", "M:3206", "M:3296", "M:3471", "M:3703", "M:3841", "M:3932", "M:4195", "M:4291", "M:4356", "M:4370", "M:4434", "M:4467"], "labels_2": ["U:27472", "High", "Medium", "Low", "M:36", "M:172", "M:224", "M:315", "M:342", "M:376", "M:485", "M:509", "M:527", "M:786", "M:910", "M:968", "M:1073", "M:1094", "M:1213", "M:1219", "M:1230", "M:1240", "M:1258", "M:1259", "M:1302", "M:1307", "M:1517", "M:1527", "M:1641", "M:1682", "M:1923", "M:1952", "M:1961", "M:2001", "M:2137", "M:2144", "M:2146", "M:2160", "M:2302", "M:2338", "M:2420", "M:2470", "M:2541", "M:2565", "M:2683", "M:2710", "M:2717", "M:2762", "M:2797", "M:2858", "M:2950", "M:2959", "M:2997", "M:3101", "M:3173", "M:3252", "M:3254", "M:3418", "M:3535", "M:3948", "M:3977", "M:4018", "M:4299", "M:4306", "M:4848", "M:4896", "M:5445", "M:5673", "M:5816", "M:7361", "M:8622", "M:8961", "M:26131"], "ged": 126}