{"graph_1": [[0, 1], [0, 2], [0, 3], [3, 4], [2, 5], [2, 6], [3, 7], [1, 8], [2, 9], [1, 10], [2, 11], [3, 12], [2, 13], [1, 14], [1, 15], [2, 16], [1, 17], [2, 18], [1, 19], [2, 20], [2, 21], [2, 22], [2, 23], [1, 24], [2, 25], [2, 26], [1, 27], [1, 28]], "graph_2": [[0, 1], [0, 2], [0, 3], [1, 4], [1, 5], [1, 6], [1, 7], [1, 8], [1, 9], [1, 10], [1, 11], [1, 12], [1, 13], [1, 14], [1, 15], [1, 16], [2, 17], [1, 18], [2, 19], [2, 20], [2, 21], [1, 22], [2, 23]], "labels_1": ["U:2822", "High", "Medium", "Low", "M:107", "M:161", "M:165", "M:231", "M:296", "M:316", "M:318", "M:329", "M:344", "M:356", "M:380", "M:457", "M:588", "M:590", "M:592", "M:593", "M:595", "M:637", "M:697", "M:708", "M:848", "M:874", "M:885", "M:897", "M:987"], "labels_2": ["U:2823", "High", "Medium", "Low", "M:50", "M:101", "M:135", "M:318", "M:333", "M:527", "M:785", "M:858", "M:1032", "M:1272", "M:1441", "M:1921", "M:2058", "M:2605", "M:2707", "M:2770", "M:3354", "M:3360", "M:51662", "M:55820"], "ged": 45}