{"graph_1": [[0, 1], [0, 2], [0, 3], [2, 4], [1, 5], [3, 6], [2, 7], [1, 8], [1, 9], [1, 10], [1, 11], [1, 12], [1, 13], [1, 14], [2, 15], [2, 16], [3, 17], [1, 18], [1, 19], [3, 20], [1, 21], [1, 22], [1, 23], [1, 24], [2, 25], [3, 26], [1, 27], [1, 28], [1, 29], [3, 30], [1, 31], [1, 32], [1, 33], [2, 34], [1, 35], [1, 36], [1, 37], [1, 38], [2, 39], [1, 40], [1, 41], [1, 42], [1, 43], [1, 44], [1, 45], [1, 46], [1, 47], [1, 48], [1, 49], [3, 50], [1, 51], [1, 52], [1, 53], [1, 54]], "graph_2": [[0, 1], [0, 2], [0, 3], [1, 4], [1, 5], [2, 6], [1, 7], [1, 8], [2, 9], [1, 10], [1, 11], [1, 12], [2, 13], [1, 14], [1, 15], [1, 16], [1, 17], [1, 18], [1, 19], [1, 20], [1, 21], [1, 22], [2, 23], [1, 24], [1, 25], [1, 26], [2, 27], [1, 28], [1, 29], [1, 30], [1, 31], [1, 32], [2, 33], [1, 34], [1, 35], [1, 36], [1, 37], [1, 38], [1, 39], [1, 40], [1, 41], [1, 42], [1, 43], [1, 44], [1, 45], [1, 46], [1, 47], [1, 48], [1, 49], [1, 50], [1, 51], [1, 52], [2, 53], [1, 54], [1, 55]], "labels_1": ["U:30088", "High", "Medium", "Low", "M:24", "M:43", "M:253", "M:407", "M:408", "M:906", "M:911", "M:1093", "M:1127", "M:1198", "M:1617", "M:1623", "M:2013", "M:2034", "M:2037", "M:2100", "M:2147", "M:2336", "M:2355", "M:2396", "M:2428", "M:2433", "M:2541", "M:2572", "M:2581", "M:2599", "M:2605", "M:2606", "M:2622", "M:2683", "M:2688", "M:2694", "M:2699", "M:2706", "M:2707", "M:2710", "M:2716", "M:2762", "M:2770", "M:2841", "M:2881", "M:2900", "M:2901", "M:2995", "M:3016", "M:3175", "M:3176", "M:3203", "M:3516", "M:3543", "M:3798"], "labels_2": ["U:30089", "High", "Medium", "Low", "M:47", "M:50", "M:110", "M:260", "M:296", "M:593", "M:714", "M:778", "M:1089", "M:1198", "M:1273", "M:1279", "M:1464", "M:2076", "M:2313", "M:2858", "M:2959", "M:2966", "M:3000", "M:3147", "M:3328", "M:3521", "M:3925", "M:3949", "M:4011", "M:4226", "M:4235", "M:4848", "M:4878", "M:4973", "M:4993", "M:5147", "M:5618", "M:5690", "M:5952", "M:5971", "M:7153", "M:7460", "M:31658", "M:34437", "M:48394", "M:58559", "M:60069", "M:68954", "M:69516", "M:76093", "M:79132", "M:91529", "M:109487", "M:115713", "M:117444", "M:134853"], "ged": 103}