{"graph_1": [[0, 1], [0, 2], [0, 3], [1, 4], [1, 5], [1, 6], [2, 7], [1, 8], [1, 9], [2, 10], [1, 11], [3, 12], [1, 13], [2, 14], [1, 15], [3, 16], [2, 17], [2, 18], [2, 19], [1, 20], [3, 21], [1, 22], [2, 23], [1, 24], [1, 25], [2, 26], [1, 27], [2, 28], [1, 29], [3, 30], [2, 31], [1, 32], [1, 33], [1, 34], [1, 35], [3, 36], [2, 37], [2, 38], [3, 39], [3, 40], [2, 41], [2, 42], [2, 43], [1, 44], [2, 45], [2, 46], [1, 47], [1, 48], [2, 49], [1, 50], [1, 51], [3, 52], [2, 53], [2, 54], [2, 55], [1, 56], [1, 57], [1, 58], [3, 59], [2, 60], [1, 61], [1, 62], [2, 63], [3, 64], [1, 65]], "graph_2": [[0, 1], [0, 2], [0, 3], [1, 4], [1, 5], [1, 6], [1, 7], [1, 8], [3, 9], [2, 10], [1, 11], [1, 12], [1, 13], [1, 14], [1, 15], [1, 16], [1, 17], [3, 18], [1, 19], [1, 20], [1, 21], [1, 22], [2, 23], [1, 24], [1, 25], [1, 26], [1, 27], [2, 28], [2, 29], [1, 30], [2, 31], [1, 32], [1, 33], [1, 34], [1, 35], [1, 36], [2, 37], [1, 38], [1, 39], [1, 40], [2, 41], [2, 42], [1, 43], [1, 44], [1, 45], [1, 46], [2, 47], [1, 48], [1, 49], [1, 50], [1, 51], [1, 52], [1, 53], [1, 54], [1, 55], [1, 56]], "labels_1": ["U:32297", "High", "Medium", "Low", "M:110", "M:314", "M:450", "M:1127", "M:1210", "M:1587", "M:1911", "M:1961", "M:1976", "M:2013", "M:2038", "M:2355", "M:2369", "M:2394", "M:2411", "M:2469", "M:2502", "M:2541", "M:2572", "M:2574", "M:2581", "M:2605", "M:2628", "M:2676", "M:2688", "M:2694", "M:2699", "M:2700", "M:2706", "M:2716", "M:2762", "M:2826", "M:2828", "M:2840", "M:2856", "M:2959", "M:2997", "M:3005", "M:3016", "M:3081", "M:3101", "M:3113", "M:3159", "M:3175", "M:3203", "M:3354", "M:3408", "M:3578", "M:3593", "M:3623", "M:3745", "M:3751", "M:3753", "M:3786", "M:3793", "M:3977", "M:3986", "M:3988", "M:4022", "M:4446", "M:4639", "M:4700"], "labels_2": ["U:32298", "High", "Medium", "Low", "M:17", "M:39", "M:110", "M:151", "M:260", "M:357", "M:377", "M:380", "M:509", "M:916", "M:920", "M:969", "M:1088", "M:1210", "M:1265", "M:1286", "M:1307", "M:1339", "M:1393", "M:1408", "M:1569", "M:1674", "M:1721", "M:1722", "M:1947", "M:1959", "M:2006", "M:2020", "M:2080", "M:2100", "M:2130", "M:2243", "M:2262", "M:2291", "M:2396", "M:2406", "M:2424", "M:2633", "M:2919", "M:2953", "M:3108", "M:3244", "M:3269", "M:3498", "M:3512", "M:3528", "M:3684", "M:3699", "M:3927", "M:3930", "M:3957", "M:3959", "M:4005"], "ged": 113}