{"graph_1": [[0, 1], [0, 2], [0, 3], [1, 4], [1, 5], [2, 6], [2, 7], [1, 8], [1, 9], [1, 10], [2, 11], [2, 12], [1, 13], [1, 14], [1, 15], [2, 16], [1, 17], [2, 18], [2, 19], [3, 20], [2, 21], [2, 22], [2, 23], [2, 24], [3, 25], [1, 26], [2, 27], [2, 28], [3, 29], [1, 30], [3, 31], [1, 32], [2, 33], [2, 34], [2, 35], [1, 36], [1, 37], [3, 38], [2, 39], [1, 40], [1, 41], [1, 42], [1, 43], [1, 44], [2, 45], [2, 46], [2, 47], [2, 48], [2, 49], [1, 50], [2, 51], [2, 52], [2, 53], [1, 54], [2, 55], [3, 56], [3, 57], [1, 58], [1, 59], [3, 60], [1, 61], [1, 62], [2, 63], [3, 64], [2, 65], [2, 66], [1, 67], [1, 68], [1, 69], [2, 70], [2, 71], [1, 72], [2, 73], [1, 74], [3, 75], [1, 76], [1, 77], [2, 78], [2, 79], [2, 80], [2, 81], [2, 82], [3, 83], [3, 84], [2, 85], [1, 86], [3, 87], [1, 88], [2, 89], [2, 90], [1, 91]], "graph_2": [[0, 1], [0, 2], [0, 3], [1, 4], [1, 5], [2, 6], [2, 7], [3, 8], [1, 9], [2, 10], [3, 11], [1, 12], [1, 13], [3, 14], [1, 15], [1, 16], [1, 17], [2, 18], [1, 19], [1, 20], [1, 21], [1, 22], [1, 23]], "labels_1": ["U:36125", "High", "Medium", "Low", "M:1", "M:3", "M:5", "M:6", "M:7", "M:14", "M:17", "M:25", "M:26", "M:32", "M:36", "M:41", "M:43", "M:55", "M:61", "M:62", "M:65", "M:79", "M:95", "M:100", "M:103", "M:140", "M:260", "M:376", "M:494", "M:605", "M:608", "M:612", "M:628", "M:639", "M:640", "M:647", "M:648", "M:661", "M:711", "M:726", "M:728", "M:733", "M:736", "M:780", "M:783", "M:784", "M:786", "M:788", "M:798", "M:802", "M:804", "M:805", "M:818", "M:830", "M:832", "M:836", "M:839", "M:851", "M:852", "M:858", "M:880", "M:991", "M:994", "M:1042", "M:1043", "M:1047", "M:1059", "M:1061", "M:1073", "M:1120", "M:1183", "M:1210", "M:1233", "M:1356", "M:1357", "M:1363", "M:1366", "M:1393", "M:1405", "M:1407", "M:1410", "M:1411", "M:1416", "M:1427", "M:1429", "M:1459", "M:1466", "M:1474", "M:1476", "M:1485", "M:1488", "M:4424"], "labels_2": ["U:36126", "High", "Medium", "Low", "M:14", "M:307", "M:327", "M:610", "M:637", "M:866", "M:1231", "M:1296", "M:1513", "M:1663", "M:2094", "M:2109", "M:2160", "M:2366", "M:2915", "M:3107", "M:3174", "M:3363", "M:3703", "M:4002"], "ged": 108}