{"graph_1": [[0, 1], [0, 2], [0, 3], [1, 4], [1, 5], [1, 6], [2, 7], [1, 8], [1, 9], [1, 10], [1, 11], [1, 12], [1, 13], [1, 14], [1, 15], [1, 16], [1, 17], [1, 18], [1, 19], [1, 20], [2, 21], [1, 22], [1, 23], [1, 24], [2, 25], [2, 26], [1, 27], [1, 28], [2, 29], [1, 30], [1, 31], [1, 32], [2, 33], [2, 34], [1, 35], [1, 36], [1, 37], [1, 38], [2, 39], [1, 40], [1, 41], [1, 42], [1, 43], [1, 44], [1, 45], [1, 46], [1, 47], [1, 48], [1, 49], [1, 50], [1, 51], [1, 52], [2, 53], [1, 54]], "graph_2": [[0, 1], [0, 2], [0, 3], [2, 4], [1, 5], [1, 6], [2, 7], [2, 8], [1, 9], [2, 10], [2, 11], [1, 12], [2, 13], [2, 14], [1, 15], [1, 16], [1, 17], [1, 18], [2, 19], [2, 20], [1, 21], [2, 22], [1, 23], [1, 24], [1, 25], [1, 26], [1, 27], [1, 28], [1, 29], [2, 30], [1, 31], [1, 32], [1, 33], [1, 34], [1, 35], [1, 36], [2, 37], [2, 38], [1, 39], [1, 40], [2, 41], [1, 42], [1, 43], [2, 44], [1, 45], [2, 46], [1, 47], [1, 48], [1, 49], [1, 50], [1, 51], [1, 52], [1, 53], [1, 54], [1, 55], [2, 56], [1, 57], [1, 58], [1, 59], [1, 60], [1, 61], [1, 62], [1, 63], [1, 64], [1, 65], [1, 66], [1, 67], [3, 68], [1, 69], [2, 70], [1, 71], [2, 72], [2, 73]], "labels_1": ["U:43252", "High", "Medium", "Low", "M:10", "M:47", "M:50", "M:70", "M:110", "M:260", "M:296", "M:316", "M:318", "M:356", "M:364", "M:539", "M:588", "M:593", "M:653", "M:780", "M:1089", "M:1092", "M:1196", "M:1197", "M:1210", "M:1276", "M:1500", "M:1580", "M:1584", "M:1639", "M:1704", "M:1784", "M:1961", "M:2353", "M:2396", "M:2502", "M:2542", "M:2571", "M:2683", "M:2700", "M:2858", "M:2959", "M:3160", "M:3481", "M:3578", "M:4226", "M:4306", "M:4896", "M:4963", "M:4973", "M:4995", "M:5418", "M:6539", "M:7153", "M:8360"], "labels_2": ["U:43253", "High", "Medium", "Low", "M:111", "M:246", "M:260", "M:277", "M:306", "M:318", "M:342", "M:527", "M:911", "M:933", "M:954", "M:1147", "M:1178", "M:1189", "M:1196", "M:1208", "M:1228", "M:1230", "M:1242", "M:1244", "M:1260", "M:1299", "M:1704", "M:1912", "M:1939", "M:1963", "M:2028", "M:2132", "M:2324", "M:2731", "M:2973", "M:3089", "M:3134", "M:3210", "M:3246", "M:3469", "M:3983", "M:4085", "M:4226", "M:4298", "M:4361", "M:4419", "M:4489", "M:4914", "M:5013", "M:6331", "M:6380", "M:6650", "M:6783", "M:6787", "M:7156", "M:8128", "M:8228", "M:9018", "M:26131", "M:30749", "M:32179", "M:32853", "M:33154", "M:39292", "M:44555", "M:46855", "M:47629", "M:55276", "M:58559", "M:59018", "M:80463", "M:80906", "M:81845", "M:92259"], "ged": 113}