{"graph_1": [[0, 1], [0, 2], [0, 3], [2, 4], [2, 5], [3, 6], [2, 7], [1, 8], [1, 9], [1, 10], [1, 11], [1, 12], [2, 13], [1, 14], [1, 15], [1, 16], [2, 17], [1, 18], [1, 19], [1, 20], [1, 21], [2, 22], [1, 23], [1, 24], [2, 25]], "graph_2": [[0, 1], [0, 2], [0, 3], [2, 4], [2, 5], [1, 6], [3, 7], [3, 8], [1, 9], [1, 10], [1, 11], [2, 12], [2, 13], [1, 14], [1, 15], [3, 16], [1, 17], [2, 18], [1, 19], [1, 20], [1, 21], [1, 22], [1, 23]], "labels_1": ["U:46852", "High", "Medium", "Low", "M:48", "M:158", "M:163", "M:236", "M:552", "M:596", "M:914", "M:953", "M:1035", "M:1148", "M:1380", "M:1500", "M:1625", "M:2081", "M:2353", "M:2406", "M:2502", "M:3052", "M:4886", "M:7153", "M:26662", "M:42011"], "labels_2": ["U:46853", "High", "Medium", "Low", "M:593", "M:596", "M:720", "M:913", "M:1132", "M:1293", "M:1693", "M:1907", "M:1967", "M:2139", "M:2140", "M:2142", "M:2724", "M:2857", "M:4366", "M:4896", "M:4973", "M:5618", "M:7323", "M:44555"], "ged": 42}