{"graph_1": [[0, 1], [0, 2], [0, 3], [3, 4], [1, 5], [1, 6], [1, 7], [2, 8], [3, 9], [1, 10], [1, 11], [3, 12], [1, 13], [1, 14], [2, 15], [1, 16], [2, 17], [1, 18], [2, 19], [1, 20], [2, 21], [2, 22], [1, 23], [1, 24]], "graph_2": [[0, 1], [0, 2], [0, 3], [1, 4], [1, 5], [1, 6], [1, 7], [1, 8], [1, 9], [1, 10], [1, 11], [2, 12], [1, 13], [1, 14], [1, 15], [1, 16], [1, 17], [1, 18], [1, 19], [1, 20], [1, 21], [1, 22], [1, 23], [1, 24], [1, 25]], "labels_1": ["U:47368", "High", "Medium", "Low", "M:1", "M:111", "M:356", "M:431", "M:627", "M:1968", "M:2022", "M:2023", "M:2144", "M:2353", "M:2433", "M:2541", "M:2580", "M:2716", "M:3101", "M:3510", "M:3578", "M:3717", "M:4022", "M:4458", "M:5418"], "labels_2": ["U:47369", "High", "Medium", "Low", "M:1203", "M:2396", "M:3173", "M:7361", "M:33004", "M:47099", "M:55247", "M:73017", "M:74868", "M:81562", "M:81845", "M:86882", "M:89039", "M:89864", "M:91542", "M:92259", "M:97921", "M:102407", "M:106918", "M:106920", "M:112552", "M:135536"], "ged": 45}