{"graph_1": [[0, 1], [0, 2], [0, 3], [1, 4], [1, 5], [1, 6], [1, 7], [1, 8], [1, 9], [1, 10], [1, 11], [2, 12], [1, 13], [2, 14], [1, 15], [1, 16], [1, 17], [1, 18], [1, 19], [1, 20], [1, 21], [1, 22], [1, 23], [1, 24], [1, 25], [1, 26], [1, 27], [1, 28], [1, 29], [1, 30], [1, 31], [1, 32], [1, 33], [1, 34], [1, 35], [1, 36], [1, 37], [1, 38], [2, 39], [1, 40], [1, 41], [1, 42], [1, 43], [1, 44], [1, 45], [1, 46]], "graph_2": [[0, 1], [0, 2], [0, 3], [2, 4], [1, 5], [3, 6], [3, 7], [2, 8], [1, 9], [3, 10], [1, 11], [2, 12], [2, 13], [2, 14], [1, 15], [1, 16], [1, 17], [2, 18], [2, 19], [1, 20], [1, 21], [1, 22], [2, 23], [1, 24]], "labels_1": ["U:47528", "High", "Medium", "Low", "M:318", "M:340", "M:1259", "M:1798", "M:2432", "M:2572", "M:2762", "M:3565", "M:3798", "M:3844", "M:3897", "M:4020", "M:4022", "M:4061", "M:4109", "M:4205", "M:4770", "M:5387", "M:5618", "M:5620", "M:6753", "M:8362", "M:26903", "M:41573", "M:52458", "M:55732", "M:56367", "M:56949", "M:62553", "M:63082", "M:64957", "M:65261", "M:66097", "M:70599", "M:71518", "M:72731", "M:74688", "M:96821", "M:104879", "M:112556", "M:114182", "M:115713", "M:140247"], "labels_2": ["U:47529", "High", "Medium", "Low", "M:16", "M:466", "M:494", "M:653", "M:923", "M:1208", "M:1220", "M:1288", "M:1917", "M:2115", "M:2174", "M:2700", "M:2791", "M:3160", "M:3793", "M:4306", "M:4979", "M:4993", "M:5902", "M:7708", "M:8622"], "ged": 66}