{"graph_1": [[0, 1], [0, 2], [0, 3], [2, 4], [1, 5], [2, 6], [2, 7], [2, 8], [1, 9], [1, 10], [1, 11], [3, 12], [2, 13], [2, 14], [1, 15], [2, 16], [3, 17], [2, 18], [1, 19], [1, 20], [1, 21], [2, 22], [1, 23], [1, 24], [1, 25], [1, 26], [3, 27], [2, 28], [1, 29], [1, 30], [2, 31], [2, 32], [1, 33], [3, 34], [3, 35], [2, 36], [1, 37], [2, 38]], "graph_2": [[0, 1], [0, 2], [0, 3], [2, 4], [2, 5], [3, 6], [3, 7], [3, 8], [3, 9], [3, 10], [3, 11], [2, 12], [3, 13], [2, 14], [1, 15], [2, 16], [3, 17], [2, 18], [3, 19], [1, 20], [3, 21], [3, 22], [3, 23], [3, 24], [2, 25], [1, 26]], "labels_1": ["U:47839", "High", "Medium", "Low", "M:785", "M:1057", "M:1183", "M:1438", "M:1485", "M:1552", "M:1584", "M:1597", "M:1608", "M:1614", "M:1615", "M:1617", "M:1641", "M:1665", "M:1673", "M:1689", "M:1722", "M:2336", "M:2395", "M:2396", "M:2433", "M:2605", "M:2716", "M:2770", "M:2881", "M:3175", "M:3384", "M:3510", "M:3555", "M:3578", "M:3618", "M:3752", "M:3753", "M:3996", "M:4027"], "labels_2": ["U:47840", "High", "Medium", "Low", "M:1103", "M:1235", "M:1389", "M:1556", "M:1760", "M:1779", "M:2382", "M:2383", "M:2394", "M:2643", "M:2664", "M:2686", "M:2719", "M:2722", "M:2840", "M:3107", "M:3148", "M:3273", "M:3564", "M:3745", "M:3798", "M:3863", "M:8622"], "ged": 60}