{"graph_1": [[0, 1], [0, 2], [0, 3], [1, 4], [3, 5], [3, 6], [1, 7], [1, 8], [2, 9], [3, 10], [1, 11], [2, 12], [1, 13], [1, 14], [1, 15], [1, 16], [1, 17], [3, 18], [1, 19], [3, 20], [1, 21], [3, 22], [1, 23], [1, 24], [2, 25], [3, 26], [1, 27], [3, 28], [3, 29], [1, 30], [3, 31], [3, 32], [1, 33], [3, 34], [1, 35], [1, 36], [1, 37], [1, 38], [1, 39], [1, 40], [1, 41], [1, 42], [1, 43], [1, 44], [1, 45], [1, 46], [1, 47], [1, 48], [1, 49], [1, 50], [1, 51], [1, 52], [1, 53], [1, 54], [1, 55], [1, 56], [1, 57], [1, 58], [1, 59], [1, 60], [1, 61], [1, 62], [1, 63], [1, 64], [1, 65]], "graph_2": [[0, 1], [0, 2], [0, 3], [1, 4], [1, 5], [1, 6], [1, 7], [1, 8], [1, 9], [1, 10], [2, 11], [1, 12], [2, 13], [1, 14], [1, 15], [1, 16], [1, 17], [1, 18], [1, 19], [1, 20], [1, 21], [1, 22], [1, 23], [1, 24], [1, 25], [1, 26]], "labels_1": ["U:48193", "High", "Medium", "Low", "M:28", "M:50", "M:70", "M:116", "M:172", "M:173", "M:208", "M:277", "M:318", "M:333", "M:442", "M:515", "M:524", "M:527", "M:585", "M:616", "M:838", "M:858", "M:969", "M:1243", "M:1260", "M:1333", "M:1345", "M:1372", "M:1375", "M:1562", "M:1653", "M:1690", "M:1726", "M:1748", "M:1909", "M:1947", "M:1949", "M:2009", "M:2273", "M:2529", "M:2985", "M:4553", "M:5463", "M:6305", "M:6678", "M:7669", "M:8132", "M:26513", "M:31410", "M:42718", "M:48738", "M:48774", "M:51255", "M:56174", "M:59315", "M:62049", "M:62376", "M:63072", "M:71530", "M:73268", "M:81591", "M:81845", "M:88125", "M:91500", "M:93040", "M:97752"], "labels_2": ["U:48194", "High", "Medium", "Low", "M:1", "M:5", "M:36", "M:61", "M:62", "M:74", "M:104", "M:107", "M:140", "M:141", "M:260", "M:609", "M:647", "M:653", "M:733", "M:736", "M:762", "M:780", "M:805", "M:839", "M:1073", "M:1210", "M:1367"], "ged": 87}