{"graph_1": [[0, 1], [0, 2], [0, 3], [2, 4], [1, 5], [2, 6], [3, 7], [1, 8], [1, 9], [2, 10], [1, 11], [1, 12], [1, 13], [2, 14], [1, 15], [2, 16], [3, 17], [2, 18], [2, 19], [3, 20], [1, 21], [2, 22], [2, 23], [2, 24], [2, 25], [1, 26], [2, 27], [1, 28], [2, 29], [3, 30], [2, 31], [2, 32], [2, 33], [2, 34], [3, 35], [2, 36], [1, 37], [2, 38], [2, 39], [1, 40], [1, 41], [2, 42], [2, 43], [2, 44], [2, 45], [2, 46], [2, 47], [2, 48], [2, 49], [2, 50], [1, 51], [2, 52], [3, 53], [1, 54], [1, 55], [2, 56], [3, 57], [2, 58], [1, 59], [1, 60], [3, 61], [2, 62], [2, 63], [2, 64], [2, 65], [2, 66], [2, 67], [2, 68]], "graph_2": [[0, 1], [0, 2], [0, 3], [1, 4], [2, 5], [1, 6], [1, 7], [3, 8], [1, 9], [2, 10], [1, 11], [2, 12], [1, 13], [1, 14], [2, 15], [3, 16], [2, 17], [3, 18], [2, 19], [3, 20], [2, 21], [3, 22], [2, 23], [2, 24], [1, 25], [3, 26], [1, 27]], "labels_1": ["U:5174", "High", "Medium", "Low", "M:32", "M:165", "M:170", "M:273", "M:296", "M:318", "M:379", "M:1036", "M:1370", "M:1385", "M:1409", "M:1527", "M:1586", "M:1917", "M:1968", "M:2000", "M:2381", "M:2403", "M:2762", "M:2792", "M:2881", "M:2916", "M:2959", "M:3450", "M:3654", "M:3744", "M:3994", "M:4023", "M:4223", "M:4226", "M:4306", "M:4963", "M:5010", "M:5500", "M:6213", "M:6539", "M:8132", "M:8665", "M:8950", "M:27773", "M:32029", "M:32587", "M:33004", "M:33615", "M:38061", "M:43936", "M:44199", "M:44665", "M:46976", "M:48304", "M:53972", "M:54286", "M:54995", "M:55820", "M:59315", "M:59369", "M:62999", "M:64969", "M:69757", "M:71530", "M:73017", "M:74458", "M:76077", "M:77561", "M:78218"], "labels_2": ["U:5175", "High", "Medium", "Low", "M:50", "M:204", "M:318", "M:527", "M:849", "M:858", "M:904", "M:912", "M:1027", "M:1198", "M:1221", "M:1385", "M:1569", "M:1586", "M:1588", "M:1965", "M:2335", "M:2455", "M:2605", "M:3354", "M:3635", "M:4148", "M:34048", "M:58559"], "ged": 85}